st7789v/__init__.py
st7789v/buffered_display.py
st7789v/colors.py
st7789v/commands.py
st7789v/display.py
st7789v/interface/__init__.py
st7789v/interface/dummy.py
st7789v/interface/io_wrapper.py
st7789v/interface/raspberry.py
st7789v-0.1.0.dist-info/LICENSE
st7789v-0.1.0.dist-info/METADATA
st7789v-0.1.0.dist-info/WHEEL
st7789v-0.1.0.dist-info/top_level.txt
st7789v-0.1.0.dist-info/RECORD
