Metadata-Version: 2.1
Name: st7789v
Version: 0.1.0
Summary: Raspberry Pi module for ST7789V display
Home-page: https://github.com/Zeroji/st7789v
Author: Zeroji
Author-email: zzeroji@gmail.com
License: UNKNOWN
Platform: UNKNOWN
Classifier: Development Status :: 3 - Alpha
Classifier: License :: OSI Approved :: GNU General Public License v3 or later (GPLv3+)
Classifier: Operating System :: POSIX :: Linux
Classifier: Programming Language :: Python :: 3
Requires-Python: >=3.5
